{
  "generated_at": "2026-03-05T09:38:04.429547",
  "runs": [
    {
      "run_id": "01819a19-cfd6-49d6-ae1e-860b82c4a660",
      "pass_rate": 100.0,
      "ve_breach_rate": 0.0,
      "sum_tokens": 0,
      "est_cost": 0,
      "breaches_per_million_tokens": 0,
      "enforcement_reliability_rate": 100.0
    },
    {
      "run_id": "06280bda-c14b-48f0-abd4-09fb0e380cd7",
      "pass_rate": 100.0,
      "ve_breach_rate": 0.0,
      "sum_tokens": 0,
      "est_cost": 0,
      "breaches_per_million_tokens": 0,
      "enforcement_reliability_rate": 100.0
    },
    {
      "run_id": "0b6fc09b-fcf8-4992-838b-4f1046bfb1a6",
      "pass_rate": 100.0,
      "ve_breach_rate": 0.0,
      "sum_tokens": 0,
      "est_cost": 0,
      "breaches_per_million_tokens": 0,
      "enforcement_reliability_rate": 100.0
    },
    {
      "run_id": "e18d297c-b260-436a-adfd-35244882086a",
      "pass_rate": 100.0,
      "ve_breach_rate": 0.0,
      "sum_tokens": 0,
      "est_cost": 0,
      "breaches_per_million_tokens": 0,
      "enforcement_reliability_rate": 100.0
    },
    {
      "run_id": "f27e34ed-bca8-4a2a-8aeb-1dba8d6d1434",
      "pass_rate": 100.0,
      "ve_breach_rate": 0.0,
      "sum_tokens": 0,
      "est_cost": 0,
      "breaches_per_million_tokens": 0,
      "enforcement_reliability_rate": 100.0
    }
  ]
}